wireless_sensor/__init__.py
wireless_sensor/_cli.py
wireless_sensor-1.0.0.dist-info/COPYING
wireless_sensor-1.0.0.dist-info/METADATA
wireless_sensor-1.0.0.dist-info/WHEEL
wireless_sensor-1.0.0.dist-info/entry_points.txt
wireless_sensor-1.0.0.dist-info/top_level.txt
wireless_sensor-1.0.0.dist-info/RECORD
